geomantic/__init__.py
geomantic/constants.py
geomantic/core.py
geomantic/demo.py
geomantic/optimizer.py
geomantic/projection.py
geomantic/visualization.py
geomantic-0.1.0.dist-info/licenses/LICENSE
geomantic-0.1.0.dist-info/METADATA
geomantic-0.1.0.dist-info/WHEEL
geomantic-0.1.0.dist-info/entry_points.txt
geomantic-0.1.0.dist-info/top_level.txt
geomantic-0.1.0.dist-info/RECORD
