Metadata-Version: 2.4
Name: geomantic
Version: 0.1.0
Summary: Approximate irregular polygons as sets of circles using differentiable rendering
Author-email: Harry O'Reilly <harry@harryoreilly.com>
License: MIT License
Project-URL: Homepage, https://github.com/horeilly/geomantic
Project-URL: Repository, https://github.com/horeilly/geomantic
Project-URL: Issues, https://github.com/horeilly/geomantic/issues
Keywords: geometry,optimization,circles,polygon,packing,pytorch,geomancy
Classifier: Development Status :: 3 - Alpha
Classifier: Intended Audience :: Science/Research
Classifier: Topic :: Scientific/Engineering :: Mathematics
Classifier: Topic :: Scientific/Engineering :: Artificial Intelligence
Classifier: License :: OSI Approved :: MIT License
Classifier: Programming Language :: Python :: 3
Classifier: Programming Language :: Python :: 3.8
Classifier: Programming Language :: Python :: 3.9
Classifier: Programming Language :: Python :: 3.10
Classifier: Programming Language :: Python :: 3.11
Classifier: Programming Language :: Python :: 3.12
Classifier: Typing :: Typed
Requires-Python: >=3.8
License-File: LICENSE
Requires-Dist: torch>=2.0.0
Requires-Dist: numpy>=1.20.0
Requires-Dist: shapely>=2.0.0
Requires-Dist: pyproj>=3.0.0
Requires-Dist: matplotlib>=3.5.0
Requires-Dist: requests>=2.25.0
Provides-Extra: dev
Requires-Dist: black>=24.8.0; extra == "dev"
Requires-Dist: flake8>=7.1.1; extra == "dev"
Requires-Dist: mypy>=1.14.0; extra == "dev"
Requires-Dist: pytest>=8.3.4; extra == "dev"
Requires-Dist: pytest-cov>=5.0.0; extra == "dev"
Requires-Dist: pytest-mock>=3.12.0; extra == "dev"
Dynamic: license-file
